zwo/__init__.py
zwo/cli.py
zwo/interpreter.py
zwo/parser.py
zwo/serialize.py
zwolang-0.3.0.dist-info/entry_points.txt
zwolang-0.3.0.dist-info/LICENSE
zwolang-0.3.0.dist-info/WHEEL
zwolang-0.3.0.dist-info/METADATA
zwolang-0.3.0.dist-info/RECORD
