Metadata-Version: 2.1
Name: zwolang
Version: 0.3.0
Summary: Python toolkit for the ZWO minilang
Home-page: https://github.com/sco1/
Author: sco1
Author-email: sco1.git@gmail.com
Requires-Python: >=3.11,<4.0
Classifier: Development Status :: 4 - Beta
Classifier: Intended Audience :: Developers
Classifier: License :: OSI Approved :: MIT License
Classifier: Operating System :: OS Independent
Classifier: Programming Language :: Python :: 3
Classifier: Programming Language :: Python :: 3.11
Classifier: Programming Language :: Python :: 3 :: Only
Classifier: Programming Language :: Python :: 3.11
Classifier: Typing :: Typed
Requires-Dist: parsimonious (>=0.10,<0.11)
Requires-Dist: rich (>=12.6,<13.0)
Requires-Dist: sco1-misc (>=0.1,<0.2)
Requires-Dist: typer[rich] (>=0.6,<0.7)
Project-URL: Repository, https://github.com/sco1/zwo
